{
    "template_id": "33c",
    "template": "SELECT MIN(cn1.name) AS first_company,\n       MIN(cn2.name) AS second_company,\n       MIN(mi_idx1.info) AS first_rating,\n       MIN(mi_idx2.info) AS second_rating,\n       MIN(t1.title) AS first_movie,\n       MIN(t2.title) AS second_movie\nFROM company_name AS cn1,\n     company_name AS cn2,\n     info_type AS it1,\n     info_type AS it2,\n     kind_type AS kt1,\n     kind_type AS kt2,\n     link_type AS lt,\n     movie_companies AS mc1,\n     movie_companies AS mc2,\n     movie_info_idx AS mi_idx1,\n     movie_info_idx AS mi_idx2,\n     movie_link AS ml,\n     title AS t1,\n     title AS t2\nWHERE cn1.country_code != '[us]'\n  AND it1.info = {}\n  AND it2.info = {}\n  AND kt1.kind IN ('tv series',\n                   'episode')\n  AND kt2.kind IN ('tv series',\n                   'episode')\n  AND lt.link IN ('sequel',\n                  'follows',\n                  'followed by')\n  AND mi_idx2.info < {}\n  AND t2.production_year BETWEEN 2000 AND 2010\n  AND lt.id = ml.link_type_id\n  AND t1.id = ml.movie_id\n  AND t2.id = ml.linked_movie_id\n  AND it1.id = mi_idx1.info_type_id\n  AND t1.id = mi_idx1.movie_id\n  AND kt1.id = t1.kind_id\n  AND cn1.id = mc1.company_id\n  AND t1.id = mc1.movie_id\n  AND ml.movie_id = mi_idx1.movie_id\n  AND ml.movie_id = mc1.movie_id\n  AND mi_idx1.movie_id = mc1.movie_id\n  AND it2.id = mi_idx2.info_type_id\n  AND t2.id = mi_idx2.movie_id\n  AND kt2.id = t2.kind_id\n  AND cn2.id = mc2.company_id\n  AND t2.id = mc2.movie_id\n  AND ml.linked_movie_id = mi_idx2.movie_id\n  AND ml.linked_movie_id = mc2.movie_id\n  AND mi_idx2.movie_id = mc2.movie_id;\n\n",
    "predicates": [
        {
            "alias": "it1",
            "column": "it1.info",
            "operator": "=",
            "data_type": "text",
            "preprocess_type": "embedding"
        },
        {
            "alias": "it2",
            "column": "it2.info",
            "operator": "=",
            "data_type": "text",
            "preprocess_type": "embedding"
        },
        {
            "alias": "mi_idx2",
            "column": "mi_idx2.info",
            "operator": "<",
            "data_type": "text",
            "preprocess_type": "embedding"
        }
    ]
}